MANIFEST.in
README.md
setup.py
requirements/base.txt
requirements/dev.txt
trading.datasets.egg-info/PKG-INFO
trading.datasets.egg-info/SOURCES.txt
trading.datasets.egg-info/dependency_links.txt
trading.datasets.egg-info/requires.txt
trading.datasets.egg-info/top_level.txt
trading/datasets/__init__.py
trading/datasets/dataset_info.py
trading/datasets/errors.py
trading/datasets/ohlcv.py
trading/datasets/orderbook.py
trading/datasets/exchange/__init__.py
trading/datasets/exchange/base.py
trading/datasets/exchange/binance.py
trading/datasets/exchange/bitmex.py
trading/datasets/exchange/bitstamp.py
trading/datasets/exchange/ftx.py
trading/datasets/tests/__init__.py
trading/datasets/tests/test_dataset_info.py
trading/datasets/tests/test_ohlcv.py
trading/datasets/tests/test_exchange/__init__.py
trading/datasets/tests/test_exchange/test_base.py
trading/datasets/tests/test_exchange/test_binance.py
trading/datasets/tests/test_exchange/test_bitmex.py
trading/datasets/tests/test_exchange/test_bitstamp.py
trading/datasets/tests/test_exchange/test_ftx.py
trading/datasets/tests/test_exchange/test_init.py
trading/datasets/tests/test_utils/__init__.py
trading/datasets/tests/test_utils/test_cache_utils.py
trading/datasets/tests/test_utils/test_datetime_utils.py
trading/datasets/tests/test_utils/test_generic_utils.py
trading/datasets/tests/test_utils/test_id_utils.py
trading/datasets/tests/test_utils/test_string_utils.py
trading/datasets/utils/__init__.py
trading/datasets/utils/cache_utils.py
trading/datasets/utils/datetime_utils.py
trading/datasets/utils/db_utils.py
trading/datasets/utils/generic_utils.py
trading/datasets/utils/id_utils.py
trading/datasets/utils/string_utils.py