Metadata-Version: 1.2
Name: trading.datasets
Version: 0.5.35
Summary: trading-datasets is a data-retrieval library for crypto asset exchanges.
Home-page: UNKNOWN
Author: Trading
License: UNKNOWN
Platform: UNKNOWN
Requires-Python: >=3.7
